{
	"name": "Table_empinfo_source",
	"properties": {
		"linkedServiceName": {
			"referenceName": "AzureSqlDatabase1",
			"type": "LinkedServiceReference"
		},
		"annotations": [],
		"type": "AzureSqlTable",
		"schema": [
			{
				"name": "empid",
				"type": "int",
				"precision": 10
			},
			{
				"name": "empname",
				"type": "varchar"
			},
			{
				"name": "skills",
				"type": "varchar"
			},
			{
				"name": "address",
				"type": "varchar"
			}
		],
		"typeProperties": {
			"schema": "dbo",
			"table": "emp_info"
		}
	}
}